coreagent/__init__.py
coreagent-0.1.0.dist-info/licenses/LICENSE
coreagent-0.1.0.dist-info/WHEEL
coreagent-0.1.0.dist-info/METADATA
coreagent-0.1.0.dist-info/RECORD
