Metadata-Version: 2.4
Name: coreagent
Version: 0.1.0
Summary: The simplest LLM Agent framework. 
Keywords: LLM,Agent,CoreAgent,AI Agent,AgentCore
Author: Kevin Wang
Maintainer: Kevin Wang
Classifier: Development Status :: 3 - Alpha
Classifier: Intended Audience :: Developers
Classifier: Topic :: Software Development :: Build Tools
Classifier: Programming Language :: Python :: 3
Classifier: Programming Language :: Python :: 3.6
Classifier: Programming Language :: Python :: 3.7
Classifier: Programming Language :: Python :: 3.8
Classifier: Programming Language :: Python :: 3.9
License-File: LICENSE
